Workbook

Sheet Comparison
B2: DLZ
B3: Group Captive: What costs would have been from 2010/2011 to 2014/2015 | H3: Date: | I3: 42095
B5: Notes
B6: Cash Flow is not reflected in the exhibit below. The Pay-In premium is paid in quarterly installments during each policy year. Dividends for each policy year normally start three years after inception and are fully paid five to seven years after inception.
B7: Cost of Capital is not reflected in the exhibit below. The collateral would have been two times the average A Fund, collected over the first three years in the program.
B8: Stock cost of $36,000 would have been incurred in 2009.
B9: Tail Fund payment is made when the group captive closes a policy year.
E11: Policy Year
B12: Captive | C12: Total | D12: 14/15 | E12: 13/14 | F12: 12/13 | G12: 11/12 | H12: 10/11
B13: Initial A Fund | C13: =SUM(D13:H13) -> 808380.08 | D13: ='Premium - Rates'!D35*Quote!$D$5 -> 187265.8 | E13: ='Premium - Rates'!E35*Quote!$D$5 -> 177954.39 | F13: ='Premium - Rates'!F35*Quote!$D$5 -> 152188.4 | G13: ='Premium - Rates'!G35*Quote!$D$5 -> 146385.79 | H13: ='Premium - Rates'!H35*Quote!$D$5 -> 144585.7
B14: Initial B Fund | C14: =SUM(D14:H14) -> 236841.12 | D14: ='Premium - Rates'!D35*Quote!$D$6 -> 54865.579 | E14: ='Premium - Rates'!E35*Quote!$D$6 -> 52137.5 | F14: ='Premium - Rates'!F35*Quote!$D$6 -> 44588.518 | G14: ='Premium - Rates'!G35*Quote!$D$6 -> 42888.456 | H14: ='Premium - Rates'!H35*Quote!$D$6 -> 42361.062
B15: Operating Costs | C15: =SUM(D15:H15) -> 496405.06 | D15: ='Premium - Rates'!D35*Quote!$D$9 -> 114995.03 | E15: ='Premium - Rates'!E35*Quote!$D$9 -> 109277.13 | F15: ='Premium - Rates'!F35*Quote!$D$9 -> 93454.913 | G15: ='Premium - Rates'!G35*Quote!$D$9 -> 89891.683 | H15: ='Premium - Rates'!H35*Quote!$D$9 -> 88786.296
B16: Surcharges and Broker Fee | C16: =SUM(D16:H16) -> 238314.38 | D16: ='Premium - Rates'!D35*Quote!$D$15 -> 55206.87 | E16: ='Premium - Rates'!E35*Quote!$D$15 -> 52461.821 | F16: ='Premium - Rates'!F35*Quote!$D$15 -> 44865.881 | G16: ='Premium - Rates'!G35*Quote!$D$15 -> 43155.244 | H16: ='Premium - Rates'!H35*Quote!$D$15 -> 42624.569
B17: Total Pay-In Amount | C17: =SUM(C13:C16) -> 1779940.6 | D17: =SUM(D13:D16) -> 412333.28 | E17: =SUM(E13:E16) -> 391830.84 | F17: =SUM(F13:F16) -> 335097.71 | G17: =SUM(G13:G16) -> 322321.17 | H17: =SUM(H13:H16) -> 318357.63
B19: Losses in 1st A Fund | C19: =SUM(D19:H19) -> 513341.79 | D19: =Losses!C11 -> 78394 | E19: =Losses!D11 -> 96441 | F19: =Losses!E11 -> 129287 | G19: =Losses!F11 -> 146385.79 | H19: =Losses!G11 -> 62834
B20: Losses in 2nd A Fund | C20: =SUM(D20:H20) -> 43050.211 | D20: =Losses!C12 -> 0 | E20: =Losses!D12 -> 0 | F20: =Losses!E12 -> 0 | G20: =Losses!F12 -> 43050.211 | H20: =Losses!G12 -> 0
B21: Losses in B Fund | C21: =SUM(D21:H21) -> 0 | D21: =Losses!C13 -> 0 | E21: =Losses!D13 -> 0 | F21: =Losses!E13 -> 0 | G21: =Losses!F13 -> 0 | H21: =Losses!G13 -> 0
B22: Operating Costs | C22: =SUM(D22:H22) -> 496405.06 | D22: =D15 -> 114995.03 | E22: =E15 -> 109277.13 | F22: =F15 -> 93454.913 | G22: =G15 -> 89891.683 | H22: =H15 -> 88786.296
B23: Surcharges and Broker Fee | C23: =SUM(D23:H23) -> 238314.38 | D23: =D16 -> 55206.87 | E23: =E16 -> 52461.821 | F23: =F16 -> 44865.881 | G23: =G16 -> 43155.244 | H23: =H16 -> 42624.569
B24: Risk Sharing | C24: =SUM(D24:H24) -> 77081.312 | D24: =SUM(D13:D15)*$C$44 -> 17856.32 | E24: =SUM(E13:E15)*$C$44 -> 16968.451 | F24: =SUM(F13:F15)*$C$44 -> 14511.591 | G24: =SUM(G13:G15)*$C$44 -> 13958.296 | H24: =SUM(H13:H15)*$C$44 -> 13786.653
B25: Tail Fund | C25: =SUM(D25:H25) -> 16691.76 | D25: =SUM(D19:D21)*$C$43 -> 2351.82 | E25: =SUM(E19:E21)*$C$43 -> 2893.23 | F25: =SUM(F19:F21)*$C$43 -> 3878.61 | G25: =SUM(G19:G21)*$C$43 -> 5683.08 | H25: =SUM(H19:H21)*$C$43 -> 1885.02
B26: Investment Income | C26: =SUM(D26:H26) -> -125426.54 | D26: =-(D13+D14)*$C$42*2 -> -29055.766 | E26: =-(E13+E14)*$C$42*2 -> -27611.027 | F26: =-(F13+F14)*$C$42*2 -> -23613.23 | G26: =-(G13+G14)*$C$42*2 -> -22712.909 | H26: =-(H13+H14)*$C$42*2 -> -22433.612
B27: Final Cost | C27: =SUM(C19:C26) -> 1259458 | D27: =SUM(D19:D26) -> 239748.27 | E27: =SUM(E19:E26) -> 250430.61 | F27: =SUM(F19:F26) -> 262384.77 | G27: =SUM(G19:G26) -> 319411.39 | H27: =SUM(H19:H26) -> 187482.93
B30: Actual Premiums for Prior Programs
C31: =SUM(D31:H31) -> 1828314 | D31: ='Premium - Rates'!O14 -> 404250 | E31: ='Premium - Rates'!O15 -> 394550 | F31: ='Premium - Rates'!O16 -> 332792 | G31: ='Premium - Rates'!O17 -> 339335 | H31: ='Premium - Rates'!O18 -> 357387
B33: Initial Cost difference: Pay-In Premium Vs. Actual Prior Premiums
B34: Dollar Amount | C34: =C17-C31 -> -48373.366 | D34: =D17-D31 -> 8083.2799 | E34: =E17-E31 -> -2719.1563 | F34: =F17-F31 -> 2305.7096 | G34: =G17-G31 -> -17013.828 | H34: =H17-H31 -> -39029.371
B35: Percentage | C35: =C34/C31 -> -0.026457909 | D35: =D34/D31 -> 0.019995745 | E35: =E34/E31 -> -0.0068917913 | F35: =F34/F31 -> 0.0069283805 | G35: =G34/G31 -> -0.050138737 | H35: =H34/H31 -> -0.10920759
B37: Final Cost Difference: After Assessments, Dividends, Close-Out Costs and Investment Income
B38: Dollar Amount | C38: =C27-C31 -> -568856.03 | D38: =D27-D31 -> -164501.73 | E38: =E27-E31 -> -144119.39 | F38: =F27-F31 -> -70407.234 | G38: =G27-G31 -> -19923.606 | H38: =H27-H31 -> -169904.07
B39: Percentage | C39: =C38/C31 -> -0.31113694 | D39: =D38/D31 -> -0.40693068 | E39: =E38/E31 -> -0.36527535 | F39: =F38/F31 -> -0.21156529 | G39: =G38/G31 -> -0.058713679 | H39: =H38/H31 -> -0.47540642
B41: Assumptions | E41: Based on 15/16 Proposal
B42: Investment Income | C42: 0.06
B43: Close-Out Costs | C43: 0.03
B44: Risk Sharing | C44: 0.05
B45: of A and B Fund

Sheet What If
B2: DLZ
B3: Group Captive: What costs would have been from 09/10 to 13/14 at various loss levels. | G3: Date: | H3: 41730
D6: DLZ premium paid over the past five years: | E6: ='Premium - Rates'!O20 -> 1828314
D7: DLZ paid and reserved losses over the past five years: | E7: =Losses!H15 -> 556392
D8: Loss Ratio: | E8: =E7/E6 -> 0.30431972
D9: Post-Dividend Savings vs. Traditional Insurance: | E9: =Comparison!C38 -> -568856.03 | F9: =E9/E6 -> -0.31113694
D11: What losses would have been at a 30% loss ratio: | E11: =E6*0.3 -> 548494.2
D12: Post-Dividend Savings vs. Traditional Insurance: | E12: -576990.97 | F12: =E12/E6 -> -0.31558637
D14: What losses would have been at a 20% loss ratio: | E14: =E6*0.2 -> 365662.8
D15: Post-Dividend Savings vs. Traditional Insurance: | E15: -765306.9 | F15: =E15/E6 -> -0.41858614
D17: What losses would have been at a 10% loss ratio: | E17: =E6*0.1 -> 182831.4
D18: Post-Dividend Savings vs. Traditional Insurance: | E18: -953623.64 | F18: =E18/E6 -> -0.52158636

Sheet Premium - Rates
C2: DLZ | K2: Captive 15/16 Quote
C3: What Captive Premiums would have been the past 5 years if your firm had been in the captive. | K3: 1/1/2015 - 1/1/2016 | L3: 115260 | M3: 106287 | N3: 154042 | O3: =SUM(L3:N3) -> 375589
K4: Captive Premium Totals
C5: Policy Year | D5: Exposure | E5: Rate | F5: Premium | G5: Surcharges | H5: Broker Fee | I5: Total | K5: Policy Year | L5: Gen. Liab. | M5: Workers Comp. | N5: Auto | O5: Total
B6: Workers Comp. | C6: 1/1/2015 - 1/1/2016 | D6: 30014700 | E6: =F6/D6*100 -> 0.35411648 | F6: =M3 -> 106287 | G6: =F6*Quote!$D$13 -> 1398.8073 | H6: =F6*Quote!$D$14 -> 15031.713 | I6: =F6+G6+H6 -> 122717.52 | K6: 1/1/2014 - 1/1/2015 | L6: =Quote!G5 -> 115260 | M6: =Quote!G7 -> 106287 | N6: =Quote!G6 -> 154042 | O6: =SUM(L6:N6) -> 375589
C7: 1/1/2014 - 1/1/2015 | D7: 30273871 | E7: =E6 -> 0.35411648 | F7: =D7*E7/100 -> 107204.77 | G7: =F7*Quote!$D$13 -> 1410.8857 | H7: =F7*Quote!$D$14 -> 15161.509 | I7: =F7+G7+H7 -> 123777.16 | K7: 1/1/2013 - 1/1/2014 | L7: =F8 -> 80119.506 | M7: =F15 -> 101937.97 | N7: =F22 -> 102887.37 | O7: =SUM(L7:N7) -> 284944.85
C8: 1/1/2013 - 1/1/2014 | D8: 22625184 | E8: =E7 -> 0.35411648 | F8: =D8*E8/100 -> 80119.506 | G8: =F8*Quote!$D$13 -> 1054.4258 | H8: =F8*Quote!$D$14 -> 11330.957 | I8: =F8+G8+H8 -> 92504.888 | K8: 1/1/2012 -1/1/2013 | L8: =F9 -> 98245.206 | M8: =F16 -> 51145.042 | N8: =F23 -> 91819.803 | O8: =SUM(L8:N8) -> 241210.05
C9: 1/1/2012 -1/1/2013 | D9: 27743754 | E9: =E8 -> 0.35411648 | F9: =D9*E9/100 -> 98245.206 | G9: =F9*Quote!$D$13 -> 1292.972 | H9: =F9*Quote!$D$14 -> 13894.396 | I9: =F9+G9+H9 -> 113432.57 | K9: 1/1/2011 - 1/1/2012 | L9: =F10 -> 92793.073 | M9: =F17 -> 34141.388 | N9: =F24 -> 99608.09 | O9: =SUM(L9:N9) -> 226542.55
C10: 1/1/2011 - 1/1/2012 | D10: 26204110 | E10: =E9 -> 0.35411648 | F10: =D10*E10/100 -> 92793.073 | G10: =F10*Quote!$D$13 -> 1221.2183 | H10: =F10*Quote!$D$14 -> 13123.325 | I10: =F10+G10+H10 -> 107137.62 | K10: 1/1/2010 - 1/1/2011 | L10: =F11 -> 89572.748 | M10: =F18 -> 25627.879 | N10: =F25 -> 103707.19 | O10: =SUM(L10:N10) -> 218907.82
C11: 1/1/2010 - 1/1/2011 | D11: 25294713 | E11: =E10 -> 0.35411648 | F11: =D11*E11/100 -> 89572.748 | G11: =F11*Quote!$D$13 -> 1178.8367 | H11: =F11*Quote!$D$14 -> 12667.888 | I11: =F11+G11+H11 -> 103419.47
K12: Actual Prior Premium
B13: General Liab. | C13: 1/1/2015 - 1/1/2016 | D13: 45500000 | E13: =F13/D13*1000 -> 2.5331868 | F13: =L3 -> 115260 | G13: =F13*Quote!$D$13 -> 1516.8979 | H13: =F13*Quote!D13 -> 1516.8979 | I13: =F13+G13+H13 -> 118293.8 | K13: Policy Year | L13: Gen. Liab. | M13: Workers Comp. | N13: Auto
C14: 1/1/2014 - 1/1/2015 | D14: 41615592 | E14: =E13 -> 2.5331868 | F14: =D14*E14/1000 -> 105420.07 | G14: =F14*Quote!$D$13 -> 1387.3979 | H14: =F14*Quote!D14 -> 14909.106 | I14: =F14+G14+H14 -> 121716.57 | K14: 1/1/2014 - 1/1/2015 | L14: 68517 | M14: 148135 | N14: 187598 | O14: =SUM(L14:N14) -> 404250
C15: 1/1/2013 - 1/1/2014 | D15: 40241000 | E15: =E14 -> 2.5331868 | F15: =D15*E15/1000 -> 101937.97 | G15: =F15*Quote!$D$13 -> 1341.5712 | H15: =F15*Quote!$D$14 -> 14416.648 | I15: =F15+G15+H15 -> 117696.19 | K15: 1/1/2013 - 1/1/2014 | L15: 71130 | M15: 125070 | N15: 198350 | O15: =SUM(L15:N15) -> 394550
C16: 1/1/2012 -1/1/2013 | D16: 20190000 | E16: =E15 -> 2.5331868 | F16: =D16*E16/1000 -> 51145.042 | G16: =F16*Quote!$D$13 -> 673.10262 | H16: =F16*Quote!$D$14 -> 7233.223 | I16: =F16+G16+H16 -> 59051.367 | K16: 1/1/2012 -1/1/2013 | L16: 63244 | M16: 114316 | N16: 155232 | O16: =SUM(L16:N16) -> 332792
C17: 1/1/2011 - 1/1/2012 | D17: 13477643 | E17: =E16 -> 2.5331868 | F17: =D17*E17/1000 -> 34141.388 | G17: =F17*Quote!$D$13 -> 449.32327 | H17: =F17*Quote!$D$14 -> 4828.4694 | I17: =F17+G17+H17 -> 39419.18 | K17: 1/1/2011 - 1/1/2012 | L17: 58529 | M17: 115566 | N17: 165240 | O17: =SUM(L17:N17) -> 339335
C18: 1/1/2010 - 1/1/2011 | D18: 10116853 | E18: =E17 -> 2.5331868 | F18: =D18*E18/1000 -> 25627.879 | G18: =F18*Quote!$D$13 -> 337.27986 | H18: =F18*Quote!$D$14 -> 3624.4405 | I18: =F18+G18+H18 -> 29589.599 | K18: 1/1/2010 - 1/1/2011 | L18: 65543 | M18: 122587 | N18: 169257 | O18: =SUM(L18:N18) -> 357387
B20: Auto Liab. | C20: 1/1/2015 - 1/1/2016 | D20: 244 | E20: =F20/D20 -> 409.90984 | F20: =Quote!H13 -> 100018 | G20: =F20*Quote!$D$13 -> 1316.3031 | H20: =F20*Quote!$D$14 -> 14145.115 | I20: =F20+G20+H20 -> 115479.42 | N20: Total | O20: =SUM(O14:O19) -> 1828314
C21: 1/1/2014 - 1/1/2015 | D21: 230 | E21: =E20 -> 409.90984 | F21: =D21*E21 -> 94279.262 | G21: =F21*Quote!$D$13 -> 1240.7775 | H21: =F21*Quote!$D$14 -> 13333.51 | I21: =F21+G21+H21 -> 108853.55
C22: 1/1/2013 - 1/1/2014 | D22: 251 | E22: =E21 -> 409.90984 | F22: =D22*E22 -> 102887.37 | G22: =F22*Quote!$D$13 -> 1354.0659 | H22: =F22*Quote!$D$14 -> 14550.918 | I22: =F22+G22+H22 -> 118792.35
C23: 1/1/2012 -1/1/2013 | D23: 224 | E23: =E22 -> 409.90984 | F23: =D23*E23 -> 91819.803 | G23: =F23*Quote!$D$13 -> 1208.4094 | H23: =F23*Quote!$D$14 -> 12985.679 | I23: =F23+G23+H23 -> 106013.89
C24: 1/1/2011 - 1/1/2012 | D24: 243 | E24: =E23 -> 409.90984 | F24: =D24*E24 -> 99608.09 | G24: =F24*Quote!$D$13 -> 1310.9084 | H24: =F24*Quote!$D$14 -> 14087.143 | I24: =F24+G24+H24 -> 115006.14
C25: 1/1/2010 - 1/1/2011 | D25: 253 | E25: =E24 -> 409.90984 | F25: =D25*E25 -> 103707.19 | G25: =F25*Quote!$D$13 -> 1364.8553 | H25: =F25*Quote!$D$14 -> 14666.861 | I25: =F25+G25+H25 -> 119738.9
B27: Auto PD | C27: 1/1/2015 - 1/1/2016 | D27: 270 | E27: =F27/D27 -> 200.08889 | F27: =Quote!H12 -> 54024 | G27: =F27*Quote!$D$13 -> 710.99162 | H27: =F27*Quote!$D$14 -> 7640.3817 | I27: =F27+G27+H27 -> 62375.373
C28: 1/1/2014 - 1/1/2015 | D28: 251 | E28: =E27 -> 200.08889 | F28: =D28*E28 -> 50222.311 | G28: =F28*Quote!$D$13 -> 660.95888 | H28: =F28*Quote!$D$14 -> 7102.7252 | I28: =F28+G28+H28 -> 57985.995
C29: 1/1/2013 - 1/1/2014 | D29: 272 | E29: =E28 -> 200.08889 | F29: =D29*E29 -> 54424.178 | G29: =F29*Quote!$D$13 -> 716.25823 | H29: =F29*Quote!$D$14 -> 7696.9771 | I29: =F29+G29+H29 -> 62837.413
C30: 1/1/2012 -1/1/2013 | D30: 245 | E30: =E29 -> 200.08889 | F30: =D30*E30 -> 49021.778 | G30: =F30*Quote!$D$13 -> 645.15906 | H30: =F30*Quote!$D$14 -> 6932.9389 | I30: =F30+G30+H30 -> 56599.876
C31: 1/1/2011 - 1/1/2012 | D31: 263 | E31: =E30 -> 200.08889 | F31: =D31*E31 -> 52623.378 | G31: =F31*Quote!$D$13 -> 692.55851 | H31: =F31*Quote!$D$14 -> 7442.2977 | I31: =F31+G31+H31 -> 60758.234
C32: 1/1/2010 - 1/1/2011 | D32: 284 | E32: =E31 -> 200.08889 | F32: =D32*E32 -> 56825.244 | G32: =F32*Quote!$D$13 -> 747.85785 | H32: =F32*Quote!$D$14 -> 8036.5496 | I32: =F32+G32+H32 -> 65609.652
B34: Total | D34: 14/15 | E34: 13/14 | F34: 12/13 | G34: 11/12 | H34: 10/11 | I34: Total
C35: Net | D35: =F7+F14+F21+F28 -> 357126.41 | E35: =F8+F15+F22+F29 -> 339369.02 | F35: =F9+F16+F23+F30 -> 290231.83 | G35: =F10+F17+F24+F31 -> 279165.93 | H35: =F11+F18+F25+F32 -> 275733.06 | I35: =SUM(D35:H35) -> 1541626.2
C36: Surcharges | D36: =G7+G14+G21+G28 -> 4700.0201 | E36: =G8+G15+G22+G29 -> 4466.3211 | F36: =G9+G16+G23+G30 -> 3819.6431 | G36: =G10+G17+G24+G31 -> 3674.0085 | H36: =G11+G18+G25+G32 -> 3628.8297 | I36: =SUM(D36:H36) -> 20288.822
C37: Broker Fee | D37: =H7+H14+H21+H28 -> 50506.85 | E37: =H8+H15+H22+H29 -> 47995.5 | F37: =H9+H16+H23+H30 -> 41046.238 | G37: =H10+H17+H24+H31 -> 39481.235 | H37: =H11+H18+H25+H32 -> 38995.739 | I37: =SUM(D37:H37) -> 218025.56
C38: Gross | D38: =SUM(D35:D37) -> 412333.28 | E38: =SUM(E35:E37) -> 391830.84 | F38: =SUM(F35:F37) -> 335097.71 | G38: =SUM(G35:G37) -> 322321.17 | H38: =SUM(H35:H37) -> 318357.63 | I38: =SUM(I35:I37) -> 1779940.6

Sheet Losses
B2: DLZ
B3: Losses
B5: Coverage | C5: 14/15 | D5: 13/14 | E5: 12/13 | F5: 11/12 | G5: 10/11 | H5: Total
B6: GL | C6: 2816 | D6: 0 | E6: 0 | F6: 69500 | G6: 0 | H6: =SUM(C6:G6) -> 72316
B7: WC | C7: 23788 | D7: 4616 | E7: 87967 | F7: 61324 | G7: 2653 | H7: =SUM(C7:G7) -> 180348
B8: Auto | C8: 51790 | D8: 91825 | E8: 41320 | F8: 58612 | G8: 60181 | H8: =SUM(C8:G8) -> 303728
B9: Total | C9: =SUM(C6:C8) -> 78394 | D9: =SUM(D6:D8) -> 96441 | E9: =SUM(E6:E8) -> 129287 | F9: =SUM(F6:F8) -> 189436 | G9: =SUM(G6:G8) -> 62834 | H9: =SUM(C9:G9) -> 556392
B11: A Fund 1 | C11: =C9 -> 78394 | D11: =D9 -> 96441 | E11: =E9 -> 129287 | F11: =Comparison!G13 -> 146385.79 | G11: =G9 -> 62834 | H11: =SUM(C11:G11) -> 513341.79
B12: A Fund 2 | C12: 0 | D12: 0 | E12: 0 | F12: =F9-F11 -> 43050.211 | G12: 0 | H12: =SUM(C12:G12) -> 43050.211
B13: B Fund | C13: 0 | D13: 0 | E13: 0 | F13: 0 | G13: 0 | H13: =SUM(C13:G13) -> 0
G15: Total | H15: =SUM(H11:H14) -> 556392

Sheet Calcs
B2: DLZ
B3: Group Captive: What costs would have been from 2010/2011 to 2014/2015 | H3: Date: | I3: 42095
B5: Notes
B6: Cash Flow is not reflected in the exhibit below. The Pay-In premium is paid in quarterly installments during each policy year. Dividends for each policy year normally start three years after inception and are fully paid five to seven years after inception.
B7: Cost of Capital is not reflected in the exhibit below. The collateral would have been two times the average A Fund, collected over the first three years in the program.
B8: Stock cost of $36,000 would have been incurred in 2009.
B9: Tail Fund payment is made when the group captive closes a policy year.
E11: Policy Year
B12: Captive | C12: Total | D12: 14/15 | E12: 13/14 | F12: 12/13 | G12: 11/12 | H12: 10/11
B13: Initial A Fund | C13: =SUM(D13:H13) -> 808380.08 | D13: ='Premium - Rates'!D35*Quote!$D$5 -> 187265.8 | E13: ='Premium - Rates'!E35*Quote!$D$5 -> 177954.39 | F13: ='Premium - Rates'!F35*Quote!$D$5 -> 152188.4 | G13: ='Premium - Rates'!G35*Quote!$D$5 -> 146385.79 | H13: ='Premium - Rates'!H35*Quote!$D$5 -> 144585.7
B14: Initial B Fund | C14: =SUM(D14:H14) -> 236841.12 | D14: ='Premium - Rates'!D35*Quote!$D$6 -> 54865.579 | E14: ='Premium - Rates'!E35*Quote!$D$6 -> 52137.5 | F14: ='Premium - Rates'!F35*Quote!$D$6 -> 44588.518 | G14: ='Premium - Rates'!G35*Quote!$D$6 -> 42888.456 | H14: ='Premium - Rates'!H35*Quote!$D$6 -> 42361.062
B15: Operating Costs | C15: =SUM(D15:H15) -> 496405.06 | D15: ='Premium - Rates'!D35*Quote!$D$9 -> 114995.03 | E15: ='Premium - Rates'!E35*Quote!$D$9 -> 109277.13 | F15: ='Premium - Rates'!F35*Quote!$D$9 -> 93454.913 | G15: ='Premium - Rates'!G35*Quote!$D$9 -> 89891.683 | H15: ='Premium - Rates'!H35*Quote!$D$9 -> 88786.296
B16: Surcharges and Broker Fee | C16: =SUM(D16:H16) -> 238314.38 | D16: ='Premium - Rates'!D35*Quote!$D$15 -> 55206.87 | E16: ='Premium - Rates'!E35*Quote!$D$15 -> 52461.821 | F16: ='Premium - Rates'!F35*Quote!$D$15 -> 44865.881 | G16: ='Premium - Rates'!G35*Quote!$D$15 -> 43155.244 | H16: ='Premium - Rates'!H35*Quote!$D$15 -> 42624.569
B17: Total Pay-In Amount | C17: =SUM(C13:C16) -> 1779940.6 | D17: =SUM(D13:D16) -> 412333.28 | E17: =SUM(E13:E16) -> 391830.84 | F17: =SUM(F13:F16) -> 335097.71 | G17: =SUM(G13:G16) -> 322321.17 | H17: =SUM(H13:H16) -> 318357.63
B19: Losses in 1st A Fund | C19: =SUM(D19:H19) -> 365663 | D19: 70496 | E19: 75000 | F19: 82333 | G19: 75000 | H19: 62834 | J19: Loss Ratio
B20: Losses in 2nd A Fund | C20: =SUM(D20:H20) -> 0 | D20: 0 | E20: 0 | F20: 0 | G20: 0 | H20: 0 | J20: =SUM(C19:C20) -> 365663 | K20: =J20/'Premium - Rates'!O20 -> 0.20000011
B21: Losses in B Fund | C21: =SUM(D21:H21) -> 0 | D21: =Losses!C13 -> 0 | E21: =Losses!D13 -> 0 | F21: =Losses!E13 -> 0 | G21: =Losses!F13 -> 0 | H21: =Losses!G13 -> 0
B22: Operating Costs | C22: =SUM(D22:H22) -> 496405.06 | D22: =D15 -> 114995.03 | E22: =E15 -> 109277.13 | F22: =F15 -> 93454.913 | G22: =G15 -> 89891.683 | H22: =H15 -> 88786.296 | J22: ='What If'!E11 -> 548494.2 | K22: 0.3
B23: Surcharges and Broker Fee | C23: =SUM(D23:H23) -> 238314.38 | D23: =D16 -> 55206.87 | E23: =E16 -> 52461.821 | F23: =F16 -> 44865.881 | G23: =G16 -> 43155.244 | H23: =H16 -> 42624.569 | J23: ='What If'!E14 -> 365662.8 | K23: 0.2
B24: Risk Sharing | C24: =SUM(D24:H24) -> 77081.312 | D24: =SUM(D13:D15)*$C$44 -> 17856.32 | E24: =SUM(E13:E15)*$C$44 -> 16968.451 | F24: =SUM(F13:F15)*$C$44 -> 14511.591 | G24: =SUM(G13:G15)*$C$44 -> 13958.296 | H24: =SUM(H13:H15)*$C$44 -> 13786.653 | J24: ='What If'!E17 -> 182831.4 | K24: 0.1
B25: Tail Fund | C25: =SUM(D25:H25) -> 10969.89 | D25: =SUM(D19:D21)*$C$43 -> 2114.88 | E25: =SUM(E19:E21)*$C$43 -> 2250 | F25: =SUM(F19:F21)*$C$43 -> 2469.99 | G25: =SUM(G19:G21)*$C$43 -> 2250 | H25: =SUM(H19:H21)*$C$43 -> 1885.02
B26: Investment Income | C26: =SUM(D26:H26) -> -125426.54 | D26: =-(D13+D14)*$C$42*2 -> -29055.766 | E26: =-(E13+E14)*$C$42*2 -> -27611.027 | F26: =-(F13+F14)*$C$42*2 -> -23613.23 | G26: =-(G13+G14)*$C$42*2 -> -22712.909 | H26: =-(H13+H14)*$C$42*2 -> -22433.612
B27: Final Cost | C27: =SUM(C19:C26) -> 1063007.1 | D27: =SUM(D19:D26) -> 231613.33 | E27: =SUM(E19:E26) -> 228346.38 | F27: =SUM(F19:F26) -> 214022.15 | G27: =SUM(G19:G26) -> 201542.31 | H27: =SUM(H19:H26) -> 187482.93
B30: Actual Premiums for Prior Programs
C31: =SUM(D31:H31) -> 1828314 | D31: ='Premium - Rates'!O14 -> 404250 | E31: ='Premium - Rates'!O15 -> 394550 | F31: ='Premium - Rates'!O16 -> 332792 | G31: ='Premium - Rates'!O17 -> 339335 | H31: ='Premium - Rates'!O18 -> 357387
B33: Initial Cost difference: Pay-In Premium Vs. Actual Prior Premiums
B34: Dollar Amount | C34: =C17-C31 -> -48373.366 | D34: =D17-D31 -> 8083.2799 | E34: =E17-E31 -> -2719.1563 | F34: =F17-F31 -> 2305.7096 | G34: =G17-G31 -> -17013.828 | H34: =H17-H31 -> -39029.371
B35: Percentage | C35: =C34/C31 -> -0.026457909 | D35: =D34/D31 -> 0.019995745 | E35: =E34/E31 -> -0.0068917913 | F35: =F34/F31 -> 0.0069283805 | G35: =G34/G31 -> -0.050138737 | H35: =H34/H31 -> -0.10920759
B37: Final Cost Difference: After Assessments, Dividends, Close-Out Costs and Investment Income
B38: Dollar Amount | C38: =C27-C31 -> -765306.9 | D38: =D27-D31 -> -172636.67 | E38: =E27-E31 -> -166203.62 | F38: =F27-F31 -> -118769.85 | G38: =G27-G31 -> -137792.69 | H38: =H27-H31 -> -169904.07
B39: Percentage | C39: =C38/C31 -> -0.41858614 | D39: =D38/D31 -> -0.42705421 | E39: =E38/E31 -> -0.42124856 | F39: =F38/F31 -> -0.35688915 | G39: =G38/G31 -> -0.40606683 | H39: =H38/H31 -> -0.47540642
B41: Assumptions | E41: Based on 15/16 Proposal
B42: Investment Income | C42: 0.06
B43: Close-Out Costs | C43: 0.03
B44: Risk Sharing | C44: 0.05
B45: of A and B Fund

Sheet Quote
C3: Quote
B5: A Fund | C5: 196947 | D5: =C5/C10 -> 0.52436839 | F5: GL | G5: 115260 | H5: 0.85 | I5: =G5/H5 -> 135600 | J5: =I5-G5 -> 20340
B6: B Fund | C6: 57702 | D6: =C6/C10 -> 0.1536307 | F6: Auto | G6: =100018+54024 -> 154042 | H6: 0.85 | I6: =G6/H6 -> 181225.88 | J6: =I6-G6 -> 27183.882
B7: Total Loss Fund | C7: =SUM(C5:C6) -> 254649 | F7: WC | G7: 106287 | H7: 0.95 | I7: =G7/H7 -> 111881.05 | J7: =I7-G7 -> 5594.0526
G8: =SUM(G5:G7) -> 375589 | J8: =SUM(J5:J7) -> 53117.935
B9: Operating Costs | C9: 120940 | D9: =C9/C10 -> 0.32200091
B10: Sub total | C10: =C7+C9 -> 375589
G12: Auto PD | H12: 54024
B13: Surcharges | C13: 4943 | D13: =C13/C10 -> 0.013160662 | G13: Auto Liab | H13: 100018
B14: Broker Fee | C14: =J8 -> 53117.935 | D14: =C14/C10 -> 0.14142569
D15: =SUM(D13:D14) -> 0.15458636
B16: Total | C16: =C10+C13+C14 -> 433649.93

Sheet Sheet1
D5: Losses : | E5: 556392
D6: Losses in 1st A Fund | E6: 513342
D7: Losses in 2nd A Fund | E7: 43050
D8: Losses in B Fund | E8: 0
D9: Operating Costs | E9: 496405
D10: Surcharges and Broker Fee | E10: 238314
D11: Risk Sharing | E11: 77081
D12: Tail Fund | E12: 16692
D13: Investment Income | E13: -125427
D14: Final Cost: | E14: =SUM(E6:E13) -> 1259457
D15: Actual Past Five Year Premium: | E15: 1828314
D16: Savings (18%): | E16: =E15-E14 -> 568857
